pyramid_exclog/__init__.py
pyramid_exclog-1.1.dist-info/LICENSE.txt
pyramid_exclog-1.1.dist-info/METADATA
pyramid_exclog-1.1.dist-info/WHEEL
pyramid_exclog-1.1.dist-info/top_level.txt
pyramid_exclog-1.1.dist-info/RECORD
