Metadata-Version: 2.1
Name: pyramid_exclog
Version: 1.1
Summary: A package which logs to a Python logger when an exception is raised by a Pyramid application
Home-page: https://github.com/Pylons/pyramid_exclog
Author: Chris McDonough
Author-email: pylons-discuss@googlegroups.com
Maintainer: Pylons Project
Maintainer-email: pylons-discuss@googlegroups.com
License: BSD-derived (Repoze)
Project-URL: Documentation, https://docs.pylonsproject.org/projects/pyramid-exclog/en/latest/index.html
Project-URL: Changelog, https://docs.pylonsproject.org/projects/pyramid-exclog/en/latest/changes.html
Project-URL: Issue Tracker, https://github.com/Pylons/pyramid_exclog/issues
Keywords: wsgi pylons pyramid mail tween exception handler
Platform: UNKNOWN
Classifier: Intended Audience :: Developers
Classifier: Programming Language :: Python
Classifier: Programming Language :: Python :: 3
Classifier: Programming Language :: Python :: 3.7
Classifier: Programming Language :: Python :: 3.8
Classifier: Programming Language :: Python :: 3.9
Classifier: Programming Language :: Python :: 3.10
Classifier: Framework :: Pyramid
Classifier: Topic :: Internet :: WWW/HTTP :: WSGI
Classifier: License :: Repoze Public License
Requires-Python: >=3.7
Provides-Extra: testing
Provides-Extra: docs
License-File: LICENSE.txt
